register_transfer/StyTR.py
register_transfer/ViT_helper.py
register_transfer/__init__.py
register_transfer/dataset.py
register_transfer/fastGuideFilter.py
register_transfer/image_utils.py
register_transfer/predict.py
register_transfer/register_sift.py
register_transfer/register_sift.pyi
register_transfer/style_transfer.py
register_transfer/style_transfer.pyi
register_transfer/transformer.py
register_transfer/utils.py
register_transfer-1.1.dist-info/LICENSE
register_transfer-1.1.dist-info/METADATA
register_transfer-1.1.dist-info/WHEEL
register_transfer-1.1.dist-info/top_level.txt
register_transfer-1.1.dist-info/RECORD
