Metadata-Version: 2.1
Name: register_transfer
Version: 1.1
Summary: Tools for image registration and style transfer in image tone field
Author: zys
Classifier: Programming Language :: Python :: 3
Classifier: License :: OSI Approved :: MIT License
Classifier: Operating System :: OS Independent
Requires-Python: >=3.6
License-File: LICENSE
Requires-Dist: Pillow
Requires-Dist: opencv-python
Requires-Dist: opencv-contrib-python
Requires-Dist: torch
Requires-Dist: numpy
Requires-Dist: natsort
Requires-Dist: tqdm
Requires-Dist: kornia
